JMeterTools-1.0.2.data/data/README.md
JMeterTools-1.0.2.data/data/requirements.txt
core/HashCode.py
core/__JMeterArguments.py
core/__JMeterHeaderManager.py
core/__JMeterHttpSampler.py
core/__JMeterRespTimeGraphVisualizer.py
core/__JMeterResponseAssert.py
core/__JMeterStatVisualizer.py
core/__JMeterSummaryReport.py
core/__JMeterTestPlan.py
core/__JMeterThreadGroup.py
core/__JMeterViewResultsFullVisualizer.py
core/__init__.py
core/base.py
core/yaml_tool.py
jmetertools/JMeter.py
jmetertools/__init__.py
jmetertools/demo.py
jmetertools/test.py
jmetertools/core/HashCode.py
jmetertools/core/__JMeterArguments.py
jmetertools/core/__JMeterHeaderManager.py
jmetertools/core/__JMeterHttpSampler.py
jmetertools/core/__JMeterRespTimeGraphVisualizer.py
jmetertools/core/__JMeterResponseAssert.py
jmetertools/core/__JMeterStatVisualizer.py
jmetertools/core/__JMeterSummaryReport.py
jmetertools/core/__JMeterTestPlan.py
jmetertools/core/__JMeterThreadGroup.py
jmetertools/core/__JMeterViewResultsFullVisualizer.py
jmetertools/core/__init__.py
jmetertools/core/base.py
jmetertools/core/yaml_tool.py
JMeterTools-1.0.2.dist-info/LICENSE
JMeterTools-1.0.2.dist-info/METADATA
JMeterTools-1.0.2.dist-info/WHEEL
JMeterTools-1.0.2.dist-info/top_level.txt
JMeterTools-1.0.2.dist-info/RECORD
