Metadata-Version: 2.1
Name: JMeterTools
Version: 1.0.2
Summary: 一款Python生成JMeter脚本的工具。
Home-page: https://gitee.com/zhangkx_z/JMeterTools
License: MIT
Platform: any
License-File: LICENSE
